{
  "impressions_history_videos_watched": [
    {
      "string_map_data": {
        "Author": {
          "value": "morganirwinxx"
        },
        "Time": {
          "timestamp": 1754341250
        }
      }
    },
    {
      "string_map_data": {
        "Author": {
          "value": "buteyard"
        },
        "Time": {
          "timestamp": 1754463816
        }
      }
    },
    {
      "string_map_data": {
        "Author": {
          "value": "goldenspooncafeglasgow"
        },
        "Time": {
          "timestamp": 1754466232
        }
      }
    },
    {
      "string_map_data": {
        "Author": {
          "value": "b0bbybroon"
        },
        "Time": {
          "timestamp": 1754466276
        }
      }
    },
    {
      "string_map_data": {
        "Author": {
          "value": "lynneywilliamson"
        },
        "Time": {
          "timestamp": 1754466299
        }
      }
    },
    {
      "string_map_data": {
        "Author": {
          "value": "lunchtimeworld"
        },
        "Time": {
          "timestamp": 1754466304
        }
      }
    },
    {
      "string_map_data": {
        "Author": {
          "value": "cocobunnieeofficial"
        },
        "Time": {
          "timestamp": 1754466355
        }
      }
    },
    {
      "string_map_data": {
        "Author": {
          "value": "natalievaldes"
        },
        "Time": {
          "timestamp": 1754502510
        }
      }
    },
    {
      "string_map_data": {
        "Author": {
          "value": "tamesidecorrespondent"
        },
        "Time": {
          "timestamp": 1754503856
        }
      }
    },
    {
      "string_map_data": {
        "Author": {
          "value": "classicues"
        },
        "Time": {
          "timestamp": 1754503861
        }
      }
    },
    {
      "string_map_data": {
        "Author": {
          "value": "travel.kamel"
        },
        "Time": {
          "timestamp": 1754503865
        }
      }
    },
    {
      "string_map_data": {
        "Author": {
          "value": "katieleighgg"
        },
        "Time": {
          "timestamp": 1754503914
        }
      }
    },
    {
      "string_map_data": {
        "Author": {
          "value": "courtroometiquette"
        },
        "Time": {
          "timestamp": 1754503923
        }
      }
    },
    {
      "string_map_data": {
        "Author": {
          "value": "paulsweeneymsp"
        },
        "Time": {
          "timestamp": 1754503963
        }
      }
    },
    {
      "string_map_data": {
        "Author": {
          "value": "roisinmccarneymusic"
        },
        "Time": {
          "timestamp": 1754503971
        }
      }
    },
    {
      "string_map_data": {
        "Author": {
          "value": "roisinmccarneymusic"
        },
        "Time": {
          "timestamp": 1754504241
        }
      }
    },
    {
      "string_map_data": {
        "Author": {
          "value": "zxh.i7"
        },
        "Time": {
          "timestamp": 1754504241
        }
      }
    },
    {
      "string_map_data": {
        "Author": {
          "value": "wednesdaynetflix"
        },
        "Time": {
          "timestamp": 1754510527
        }
      }
    },
    {
      "string_map_data": {
        "Author": {
          "value": "onedayatatimelass"
        },
        "Time": {
          "timestamp": 1754557392
        }
      }
    },
    {
      "string_map_data": {
        "Author": {
          "value": "thelardnerladiesjournal"
        },
        "Time": {
          "timestamp": 1754567711
        }
      }
    },
    {
      "string_map_data": {
        "Author": {
          "value": "katiebeevlogs"
        },
        "Time": {
          "timestamp": 1754593946
        }
      }
    },
    {
      "string_map_data": {
        "Author": {
          "value": "deezer"
        },
        "Time": {
          "timestamp": 1754608561
        }
      }
    },
    {
      "string_map_data": {
        "Author": {
          "value": "foliosociety"
        },
        "Time": {
          "timestamp": 1754740577
        }
      }
    },
    {
      "string_map_data": {
        "Author": {
          "value": "hannahgrande.pw"
        },
        "Time": {
          "timestamp": 1754740581
        }
      }
    },
    {
      "string_map_data": {
        "Author": {
          "value": "fortnite"
        },
        "Time": {
          "timestamp": 1754740594
        }
      }
    },
    {
      "string_map_data": {
        "Author": {
          "value": "motorforms"
        },
        "Time": {
          "timestamp": 1754740631
        }
      }
    },
    {
      "string_map_data": {
        "Author": {
          "value": "ell.ess.see"
        },
        "Time": {
          "timestamp": 1754782361
        }
      }
    },
    {
      "string_map_data": {
        "Author": {
          "value": "fortnite"
        },
        "Time": {
          "timestamp": 1754869025
        }
      }
    },
    {
      "string_map_data": {
        "Author": {
          "value": "cursed_jetta_r"
        },
        "Time": {
          "timestamp": 1754870785
        }
      }
    },
    {
      "string_map_data": {
        "Author": {
          "value": "morganirwinxx"
        },
        "Time": {
          "timestamp": 1754903141
        }
      }
    },
    {
      "string_map_data": {
        "Author": {
          "value": "cocobunnieeofficial"
        },
        "Time": {
          "timestamp": 1754944038
        }
      }
    },
    {
      "string_map_data": {
        "Author": {
          "value": "winging_mamahood"
        },
        "Time": {
          "timestamp": 1754944177
        }
      }
    },
    {
      "string_map_data": {
        "Author": {
          "value": "lowrirose"
        },
        "Time": {
          "timestamp": 1754944195
        }
      }
    },
    {
      "string_map_data": {
        "Author": {
          "value": "f.scottishwindows"
        },
        "Time": {
          "timestamp": 1754944300
        }
      }
    },
    {
      "string_map_data": {
        "Author": {
          "value": "reptiliancouncil"
        },
        "Time": {
          "timestamp": 1754341240
        }
      }
    },
    {
      "string_map_data": {
        "Author": {
          "value": "lynneywilliamson"
        },
        "Time": {
          "timestamp": 1754341240
        }
      }
    },
    {
      "string_map_data": {
        "Author": {
          "value": "morganirwinxx"
        },
        "Time": {
          "timestamp": 1754341254
        }
      }
    },
    {
      "string_map_data": {
        "Author": {
          "value": "morganirwinxx"
        },
        "Time": {
          "timestamp": 1754463488
        }
      }
    },
    {
      "string_map_data": {
        "Author": {
          "value": "buteyard"
        },
        "Time": {
          "timestamp": 1754463871
        }
      }
    },
    {
      "string_map_data": {
        "Author": {
          "value": "goldenspooncafeglasgow"
        },
        "Time": {
          "timestamp": 1754466240
        }
      }
    },
    {
      "string_map_data": {
        "Author": {
          "value": "b0bbybroon"
        },
        "Time": {
          "timestamp": 1754466288
        }
      }
    },
    {
      "string_map_data": {
        "Author": {
          "value": "lunchtimeworld"
        },
        "Time": {
          "timestamp": 1754466332
        }
      }
    },
    {
      "string_map_data": {
        "Author": {
          "value": "lynneywilliamson"
        },
        "Time": {
          "timestamp": 1754466332
        }
      }
    },
    {
      "string_map_data": {
        "Author": {
          "value": "cocobunnieeofficial"
        },
        "Time": {
          "timestamp": 1754486708
        }
      }
    },
    {
      "string_map_data": {
        "Author": {
          "value": "natalievaldes"
        },
        "Time": {
          "timestamp": 1754502529
        }
      }
    },
    {
      "string_map_data": {
        "Author": {
          "value": "boxfreshglasgow"
        },
        "Time": {
          "timestamp": 1754503830
        }
      }
    },
    {
      "string_map_data": {
        "Author": {
          "value": "joeroganexperience"
        },
        "Time": {
          "timestamp": 1754503830
        }
      }
    },
    {
      "string_map_data": {
        "Author": {
          "value": "tamesidecorrespondent"
        },
        "Time": {
          "timestamp": 1754503852
        }
      }
    },
    {
      "string_map_data": {
        "Author": {
          "value": "rosieandharry"
        },
        "Time": {
          "timestamp": 1754503852
        }
      }
    },
    {
      "string_map_data": {
        "Author": {
          "value": "travel.kamel"
        },
        "Time": {
          "timestamp": 1754503909
        }
      }
    },
    {
      "string_map_data": {
        "Author": {
          "value": "classicues"
        },
        "Time": {
          "timestamp": 1754503909
        }
      }
    },
    {
      "string_map_data": {
        "Author": {
          "value": "katieleighgg"
        },
        "Time": {
          "timestamp": 1754503909
        }
      }
    },
    {
      "string_map_data": {
        "Author": {
          "value": "courtroometiquette"
        },
        "Time": {
          "timestamp": 1754503960
        }
      }
    },
    {
      "string_map_data": {
        "Author": {
          "value": "paulsweeneymsp"
        },
        "Time": {
          "timestamp": 1754503960
        }
      }
    },
    {
      "string_map_data": {
        "Author": {
          "value": "katieleighgg2"
        },
        "Time": {
          "timestamp": 1754507056
        }
      }
    },
    {
      "string_map_data": {
        "Author": {
          "value": "roisinmccarneymusic"
        },
        "Time": {
          "timestamp": 1754507056
        }
      }
    },
    {
      "string_map_data": {
        "Author": {
          "value": "roisinmccarneymusic"
        },
        "Time": {
          "timestamp": 1754507056
        }
      }
    },
    {
      "string_map_data": {
        "Author": {
          "value": "zxh.i7"
        },
        "Time": {
          "timestamp": 1754507056
        }
      }
    },
    {
      "string_map_data": {
        "Author": {
          "value": "wednesdaynetflix"
        },
        "Time": {
          "timestamp": 1754557290
        }
      }
    },
    {
      "string_map_data": {
        "Author": {
          "value": "onedayatatimelass"
        },
        "Time": {
          "timestamp": 1754564437
        }
      }
    },
    {
      "string_map_data": {
        "Author": {
          "value": "thelardnerladiesjournal"
        },
        "Time": {
          "timestamp": 1754569307
        }
      }
    },
    {
      "string_map_data": {
        "Author": {
          "value": "katiebeevlogs"
        },
        "Time": {
          "timestamp": 1754608228
        }
      }
    },
    {
      "string_map_data": {
        "Author": {
          "value": "deezer"
        },
        "Time": {
          "timestamp": 1754665426
        }
      }
    },
    {
      "string_map_data": {
        "Author": {
          "value": "brianlimond"
        },
        "Time": {
          "timestamp": 1754676895
        }
      }
    },
    {
      "string_map_data": {
        "Author": {
          "value": "hannahgrande.pw"
        },
        "Time": {
          "timestamp": 1754740582
        }
      }
    },
    {
      "string_map_data": {
        "Author": {
          "value": "foliosociety"
        },
        "Time": {
          "timestamp": 1754740582
        }
      }
    },
    {
      "string_map_data": {
        "Author": {
          "value": "davidmenziescosplay"
        },
        "Time": {
          "timestamp": 1754740638
        }
      }
    },
    {
      "string_map_data": {
        "Author": {
          "value": "fortnite"
        },
        "Time": {
          "timestamp": 1754740638
        }
      }
    },
    {
      "string_map_data": {
        "Author": {
          "value": "therealtamcowan"
        },
        "Time": {
          "timestamp": 1754740638
        }
      }
    },
    {
      "string_map_data": {
        "Author": {
          "value": "motorforms"
        },
        "Time": {
          "timestamp": 1754750086
        }
      }
    },
    {
      "string_map_data": {
        "Author": {
          "value": "hustlenovel"
        },
        "Time": {
          "timestamp": 1754750086
        }
      }
    },
    {
      "string_map_data": {
        "Author": {
          "value": "ell.ess.see"
        },
        "Time": {
          "timestamp": 1754782349
        }
      }
    },
    {
      "string_map_data": {
        "Author": {
          "value": "ell.ess.see"
        },
        "Time": {
          "timestamp": 1754824328
        }
      }
    },
    {
      "string_map_data": {
        "Author": {
          "value": "fortnite"
        },
        "Time": {
          "timestamp": 1754869076
        }
      }
    },
    {
      "string_map_data": {
        "Author": {
          "value": "cursed_jetta_r"
        },
        "Time": {
          "timestamp": 1754903007
        }
      }
    },
    {
      "string_map_data": {
        "Author": {
          "value": "morganirwinxx"
        },
        "Time": {
          "timestamp": 1754931891
        }
      }
    },
    {
      "string_map_data": {
        "Author": {
          "value": "cocobunnieeofficial"
        },
        "Time": {
          "timestamp": 1754944285
        }
      }
    },
    {
      "string_map_data": {
        "Author": {
          "value": "hannah_brooks_world"
        },
        "Time": {
          "timestamp": 1754463768
        }
      }
    },
    {
      "string_map_data": {
        "Author": {
          "value": "maxwarner_tate"
        },
        "Time": {
          "timestamp": 1754585128
        }
      }
    },
    {
      "string_map_data": {
        "Author": {
          "value": "thejeremyvine"
        },
        "Time": {
          "timestamp": 1754918177
        }
      }
    }
  ]
}