{
  "story_activities_quizzes": [
    {
      "title": "foodie_girl_adventures",
      "string_list_data": [
        {
          "value": "Fillet",
          "timestamp": 1699378615
        }
      ]
    },
    {
      "title": "gusmack1",
      "string_list_data": [
        {
          "value": "So called blue ticks getting paid abusing their followers?",
          "timestamp": 1697585187
        }
      ]
    },
    {
      "title": "theweegieroll",
      "string_list_data": [
        {
          "value": "Stew",
          "timestamp": 1660723121
        }
      ]
    },
    {
      "title": "kirstieskitchen",
      "string_list_data": [
        {
          "value": "Tower",
          "timestamp": 1659876810
        }
      ]
    },
    {
      "title": "lauzlikes",
      "string_list_data": [
        {
          "value": "Option 0",
          "timestamp": 1657993260
        }
      ]
    },
    {
      "title": "gusmack1",
      "string_list_data": [
        {
          "value": "Option 1",
          "timestamp": 1657106250
        }
      ]
    },
    {
      "title": "chateauxuk_",
      "string_list_data": [
        {
          "value": "Option 1",
          "timestamp": 1638517645
        }
      ]
    },
    {
      "title": "gusmack1",
      "string_list_data": [
        {
          "value": "Option 2",
          "timestamp": 1629275026
        }
      ]
    },
    {
      "title": "seanssupper",
      "string_list_data": [
        {
          "value": "Mexican",
          "timestamp": 1605376777
        }
      ]
    },
    {
      "title": "keratins_by_lauren_",
      "string_list_data": [
        {
          "value": "BATH BOMBS",
          "timestamp": 1603894975
        }
      ]
    },
    {
      "title": "gusmack1",
      "string_list_data": [
        {
          "value": "Option 1",
          "timestamp": 1598180281
        }
      ]
    },
    {
      "title": "gusmack1",
      "string_list_data": [
        {
          "value": "Option 1",
          "timestamp": 1595585144
        }
      ]
    },
    {
      "title": "gusmack1",
      "string_list_data": [
        {
          "value": "Option 1",
          "timestamp": 1593678970
        }
      ]
    },
    {
      "title": "botecodobrasil",
      "string_list_data": [
        {
          "value": "Option 0",
          "timestamp": 1592998390
        }
      ]
    },
    {
      "title": "gusmack1",
      "string_list_data": [
        {
          "value": "Option 0",
          "timestamp": 1588432228
        }
      ]
    },
    {
      "title": "guyforallseasons",
      "string_list_data": [
        {
          "value": "Option 1",
          "timestamp": 1585676317
        }
      ]
    },
    {
      "title": "ciborico",
      "string_list_data": [
        {
          "value": "Catalonia",
          "timestamp": 1581796608
        }
      ]
    },
    {
      "title": "kirstieskitchen",
      "string_list_data": [
        {
          "value": "Happy anniversary",
          "timestamp": 1579721854
        }
      ]
    },
    {
      "title": "gusmack1",
      "string_list_data": [
        {
          "value": "Option 0",
          "timestamp": 1579531043
        }
      ]
    },
    {
      "title": "gusmack1",
      "string_list_data": [
        {
          "value": "Option 2",
          "timestamp": 1563718706
        }
      ]
    },
    {
      "title": "seanssupper",
      "string_list_data": [
        {
          "value": "Option 3",
          "timestamp": 1561736095
        }
      ]
    }
  ]
}